rust_paillier-0.1.0.dist-info/METADATA
rust_paillier-0.1.0.dist-info/WHEEL
rust_paillier/__init__.pyi
rust_paillier/__init__.py
rust_paillier/par/__init__.pyi
rust_paillier/par/__init__.py
rust_paillier/rust_paillier.cpython-38-darwin.so
rust_paillier-0.1.0.dist-info/RECORD
