Metadata-Version: 2.1
Name: rust_paillier
Version: 0.1.0
Classifier: Programming Language :: Rust
Classifier: Programming Language :: Python :: Implementation :: CPython
Classifier: Programming Language :: Python :: Implementation :: PyPy
Summary: paillier tensor implemented using rust
Requires-Python: >=3.6
